xhmonitor/__init__.py
xhmonitor/monitor.py
xhmonitor/test_monitor.py
xhmonitor-0.0.2.dist-info/METADATA
xhmonitor-0.0.2.dist-info/WHEEL
xhmonitor-0.0.2.dist-info/top_level.txt
xhmonitor-0.0.2.dist-info/RECORD
