Metadata-Version: 2.1
Name: xhmonitor
Version: 0.0.2
Summary: a lib for Performance monitoring
Home-page: https://github.com/lamborghini1993/mypypi/tree/master/xhmonitor
Author: lamborghini1993
Author-email: 1323242382@qq.com
License: UNKNOWN
Platform: UNKNOWN
Classifier: Programming Language :: Python :: 3
Classifier: License :: OSI Approved :: MIT License
Classifier: Operating System :: OS Independent
Requires-Python: >=3.6
Requires-Dist: pyprof2calltree
